reader_vl/.env
reader_vl/docs/schemas.py
reader_vl/docs/structure/__init__.py
reader_vl/docs/structure/core.py
reader_vl/docs/structure/prompt.py
reader_vl/docs/structure/registry.py
reader_vl/docs/structure/schemas.py
reader_vl/docs/utils.py
reader_vl/docs/yolo/__init__.py
reader_vl/docs/yolo/yolo.py
reader_vl/document_reader/__init__.py
reader_vl/document_reader/base.py
reader_vl/document_reader/docx/__init__.py
reader_vl/document_reader/docx/reader.py
reader_vl/document_reader/pdf/__init__.py
reader_vl/document_reader/pdf/reader.py
reader_vl/llm/__init__.py
reader_vl/llm/client.py
reader_vl/llm/openai/__init__.py
reader_vl/llm/openai/client.py
reader_vl/llm/schemas.py
reader_vl/llm/utils.py
reader_vl/llm/vllm/__init__.py
reader_vl/llm/vllm/client.py
reader_vl/models/utils.py
reader_vl-0.1.0.dist-info/METADATA
reader_vl-0.1.0.dist-info/WHEEL
reader_vl-0.1.0.dist-info/RECORD
